playlist2podcast/__init__.py
playlist2podcast/playlist_2_podcast.py
playlist2podcast/util.py
playlist2podcast-2026.2.1.dist-info/WHEEL
playlist2podcast-2026.2.1.dist-info/entry_points.txt
playlist2podcast-2026.2.1.dist-info/METADATA
playlist2podcast-2026.2.1.dist-info/RECORD
