Metadata-Version: 2.3
Name: playlist2podcast
Version: 2026.2.1
Summary: Creates podcast feed from playlist URL
Author: Marvin8
Author-email: Marvin8 <marvin8@tuta.io>
License: AGPL-3.0-or-later
Classifier: Development Status :: 5 - Production/Stable
Classifier: Environment :: Console
Classifier: Operating System :: OS Independent
Classifier: Programming Language :: Python
Classifier: Programming Language :: Python :: 3.10
Classifier: Programming Language :: Python :: 3.11
Classifier: Programming Language :: Python :: 3.12
Classifier: Programming Language :: Python :: 3.13
Classifier: Topic :: Utilities
Requires-Dist: feedgen~=1.0.0
Requires-Dist: loguru~=0.7.3
Requires-Dist: msgspec~=0.20.0
Requires-Dist: pillow~=12.1.0
Requires-Dist: pycryptodomex~=3.23.0
Requires-Dist: requests~=2.32.5
Requires-Dist: tomli-w~=1.2.0
Requires-Dist: typer~=0.21.1
Requires-Dist: whenever~=0.9.5
Requires-Dist: yt-dlp~=2026.1.31
Requires-Python: >=3.10, <3.14
Project-URL: Changelog, https://codeberg.org/PyYtTools/Playlist2Podcasts/src/branch/main/CHANGELOG.md
Project-URL: Documentation, https://codeberg.org/PyYtTools/Playlist2Podcasts/src/branch/main/README.md
Project-URL: Issues, https://codeberg.org/PyYtTools/Playlist2Podcasts/issues
Project-URL: Source, https://codeberg.org/PyYtTools/Playlist2Podcasts
